{
    "instruments": {
        "Piano_treble": {
            "nonterminals": ["S", "A", "B", "M", "H", "H1", "M1", "M2", "H2"],
            "terminals": ["C", "D", "E", "F", "G"],
            "start": "S",
            "structure_rules": [
                { "left": ["S"], "right": ["AABA"] },
                { "left": ["A", "A", "A"], "right": ["MH", "MH", "MH"] },
                { "left": ["B"], "right": ["H1", "M1", "M2", "H2"] }
            ],
            "tone_rules": [
                { "left": ["M", "M", "M"], "right": [
                    [
                        { "tone": "C", "length": "quarter", "octave": 2, "dynamics": "ff", "operation": {"transpose": 1}},
                        { "tone": "D", "length": "quarter", "octave": 2, "dynamics": "ff", "operation": {"transpose": 1}},
                        { "tone": "E", "length": "quarter", "octave": 2, "dynamics": "ff", "operation": {"transpose": 1}},
                        { "tone": "F", "length": "quarter", "octave": 2, "dynamics": "ff", "operation": {"transpose": 1}}
                    ], 
                    [
                        { "tone": "C", "length": "quarter", "octave": 2, "dynamics": "ff", "operation": {"counterpoint": true} },
                        { "tone": "D", "length": "quarter", "octave": 2, "dynamics": "ff", "operation": {"counterpoint": true} },
                        { "tone": "E", "length": "quarter", "octave": 2, "dynamics": "ff", "operation": {"counterpoint": true} },
                        { "tone": "F", "length": "quarter", "octave": 2, "dynamics": "ff", "operation": {"counterpoint": true} }
                    ], 
                    [
                        { "tone": "C", "length": "quarter", "octave": 2, "dynamics": "ff", "operation": "none" },
                        { "tone": "D", "length": "quarter", "octave": 2, "dynamics": "ff", "operation": "none" },
                        { "tone": "E", "length": "quarter", "octave": 2, "dynamics": "ff", "operation": "none" },
                        { "tone": "F", "length": "quarter", "octave": 2, "dynamics": "ff", "operation": "none" }
                    ]
                    ] 
                },
                { "left": ["H", "H", "H"], "right": [
                    [
                        { "chord": ["D", "F", "A"], "length": "whole", "dynamics": "ff", "operation": "none" }
                    ], 
                    [
                        { "chord": ["D", "F", "A"], "length": "whole", "dynamics": "ff", "operation": "none" }
                    ], 
                    [
                        { "chord": ["D", "F", "A"], "length": "whole", "dynamics": "ff", "operation": "none" }
                    ]
                    ] 
                },
                { "left": ["M1", "M2"], "right": [
                    [{ "tone": "C", "length": "whole", "octave": 2, "dynamics": "p", "operation": "none" }],
                    [{ "tone": "C", "length": "whole", "octave": 2, "dynamics": "p", "operation": "none" }]
                    ] 
                },
                { "left": ["H1", "H2"], "right": [
                    [
                        { "chord": ["C", "E", "G"], "length": "half", "octave": 2, "dynamics": "mf", "operation": "none" },
                        { "chord": ["C", "E", "G"], "length": "half", "octave": 2, "dynamics": "mf", "operation": "none" }
                    ],
                    [
                        { "chord": ["C", "E", "G"], "length": "half", "octave": 2, "dynamics": "mf", "operation": "none" },
                        { "chord": ["C", "E", "G"], "length": "half", "octave": 2, "dynamics": "mf", "operation": "none" }
                    ]
                    ] 
                }
            ]
        },
        "Piano_bass": {
            "nonterminals": ["S1", "A", "B", "M", "H", "H1", "M1", "M2", "H2"],
            "terminals": ["C4", "D4", "E4", "F4", "G4"],
            "start": "S1",
            "structure_rules": [
                { "left": ["S1"], "right": ["AABA"] },
                { "left": ["A", "A", "A"], "right": ["MH", "MH", "MH"] },
                { "left": ["B"], "right": ["H1", "M1", "M2", "H2"] }
            ],
            "tone_rules": [
                { "left": ["M", "M", "M"], "right": [
                    [
                        { "tone": "C", "length": "quarter", "octave": 2, "dynamics": "p", "operation": "none" },
                        { "tone": "D", "length": "quarter", "octave": 2, "dynamics": "p", "operation": "none" },
                        { "tone": "E", "length": "quarter", "octave": 2, "dynamics": "p", "operation": "none" },
                        { "tone": "F", "length": "quarter", "octave": 2, "dynamics": "p", "operation": "none" }
                    ], 
                    [
                        { "tone": "C", "length": "quarter", "octave": 2, "dynamics": "p", "operation": "none" },
                        { "tone": "D", "length": "quarter", "octave": 2, "dynamics": "p", "operation": "none" },
                        { "tone": "E", "length": "quarter", "octave": 2, "dynamics": "p", "operation": "none" },
                        { "tone": "F", "length": "quarter", "octave": 2, "dynamics": "p", "operation": "none" }
                    ], 
                    [
                        { "tone": "C", "length": "quarter", "octave": 2, "dynamics": "p", "operation": "none" },
                        { "tone": "D", "length": "quarter", "octave": 2, "dynamics": "p", "operation": "none" },
                        { "tone": "E", "length": "quarter", "octave": 2, "dynamics": "p", "operation": "none" },
                        { "tone": "F", "length": "quarter", "octave": 2, "dynamics": "p", "operation": "none" }
                    ]
                    ] 
                },
                { "left": ["H", "H", "H"], "right": [
                    [
                        { "chord": ["D", "F", "A"], "length": "whole", "dynamics": "ff", "operation": "none" }
                    ], 
                    [
                        { "chord": ["D", "F", "A"], "length": "whole", "dynamics": "ff", "operation": "none" }
                    ], 
                    [
                        { "chord": ["D", "F", "A"], "length": "whole", "dynamics": "ff", "operation": "none" }
                    ]
                    ] 
                },
                { "left": ["M1", "M2"], "right": [
                    [{ "tone": "C", "length": "whole", "octave": 2, "dynamics": "p", "operation": "none" }],
                    [{ "tone": "C", "length": "whole", "octave": 2, "dynamics": "p", "operation": "none" }]
                    ] 
                },
                { "left": ["H1", "H2"], "right": [
                    [
                        { "chord": ["C", "E", "G"], "length": "half", "octave": 2, "dynamics": "mf", "operation": "none" },
                        { "chord": ["C", "E", "G"], "length": "half", "octave": 2, "dynamics": "mf", "operation": "none" }
                    ],
                    [
                        { "chord": ["C", "E", "G"], "length": "half", "octave": 2, "dynamics": "mf", "operation": "none" },
                        { "chord": ["C", "E", "G"], "length": "half", "octave": 2, "dynamics": "mf", "operation": "none" }
                    ]
                    ] 
                }
            ]
        },
        "Violin": {
            "nonterminals": ["S2", "A", "B", "M", "H", "H1", "M1", "M2", "H2"],
            "terminals": ["G", "A", "B", "C"],
            "start": "S2",
            "structure_rules": [
                { "left": ["S2"], "right": ["AABA"] },
                { "left": ["A", "A", "A"], "right": ["MH", "MH", "MH"] },
                { "left": ["B"], "right": ["H1", "M1", "M2", "H2"] }
            ],
            "tone_rules": [
                { "left": ["M", "M", "M"], "right": [
                    [
                        { "tone": "C", "length": "quarter", "octave": 1, "dynamics": "piano", "operation": "none" },
                        { "tone": "F", "length": "quarter", "octave": 1, "dynamics": "piano", "operation": "none" },
                        { "tone": "G", "length": "quarter", "octave": 1, "dynamics": "piano", "operation": "none" },
                        { "tone": "H", "length": "quarter", "octave": 1, "dynamics": "piano", "operation": "none" }
                    ],
                    [
                        { "tone": "C", "length": "quarter", "octave": 1, "dynamics": "piano", "operation": "none" },
                        { "tone": "F", "length": "quarter", "octave": 1, "dynamics": "piano", "operation": "none" },
                        { "tone": "G", "length": "quarter", "octave": 1, "dynamics": "piano", "operation": "none" },
                        { "tone": "H", "length": "quarter", "octave": 1, "dynamics": "piano", "operation": "none" }
                    ],
                    [
                        { "tone": "H", "length": "quarter", "octave": 1, "dynamics": "piano", "operation": "none" },
                        { "tone": "A", "length": "quarter", "octave": 1, "dynamics": "piano", "operation": "none" },
                        { "tone": "G", "length": "quarter", "octave": 1, "dynamics": "piano", "operation": "none" },
                        { "tone": "F", "length": "quarter", "octave": 1, "dynamics": "piano", "operation": "none" }
                    ]
                    ] 
                },
                { "left": ["H", "H", "H"], "right": [
                    [
                        { "chord": ["D", "F", "A"], "length": "whole", "dynamics": "fortissimo", "operation": "none" }
                    ], 
                    [
                        { "chord": ["D", "F", "A"], "length": "whole", "dynamics": "fortissimo", "operation": "none" }
                    ], 
                    [
                        { "chord": ["D", "F", "A"], "length": "whole", "dynamics": "fortissimo", "operation": "none" }
                    ]
                    ] 
                },
                { "left": ["M1", "M2"], "right": [
                    [{ "tone": "C", "length": "whole", "octave": 2, "dynamics": "piano", "operation": "none" }],
                    [{ "tone": "C", "length": "whole", "octave": 2, "dynamics": "piano", "operation": "none" }]
                    ] 
                },
                { "left": ["H1", "H2"], "right": [
                    [
                        { "chord": ["C", "E", "G"], "length": "half", "octave": 2, "dynamics": "mezzo-forte", "operation": "none" },
                        { "chord": ["C", "E", "G"], "length": "half", "octave": 2, "dynamics": "mezzo-forte", "operation": "none" }
                    ],
                    [
                        { "chord": ["C", "E", "G"], "length": "half", "octave": 2, "dynamics": "mezzo-forte", "operation": "none" },
                        { "chord": ["C", "E", "G"], "length": "half", "octave": 2, "dynamics": "mezzo-forte", "operation": "none" }
                    ]
                    ] 
                }
            ]
        }
    },
    "Q": [
        { "Piano_bass": 0, "Piano_treble": 0, "Violin": 0 },
        { "Piano_bass": 1, "Piano_treble": 1, "Violin": 1 },
        { "Piano_bass": 2, "Piano_treble": 2, "Violin": 2 },
        { "Piano_bass": 3, "Piano_treble": 3, "Violin": 3 },
        { "Piano_bass": 4, "Piano_treble": 4, "Violin": 4 },
        { "Piano_bass": 5, "Piano_treble": 5, "Violin": 5 },
        { "Piano_bass": 6, "Piano_treble": 6, "Violin": 6 },
        { "Piano_bass": 7, "Piano_treble": 7, "Violin": 7 }
    ]
}